any_parser_rt/__init__.py
any_parser_rt/any_parser_rt.py
any_parser_rt-0.0.3.dist-info/METADATA
any_parser_rt-0.0.3.dist-info/WHEEL
any_parser_rt-0.0.3.dist-info/RECORD
