Metadata-Version: 2.1
Name: any-parser-rt
Version: 0.0.3
Summary: 
Author: Rachel Hu
Author-email: goldpiggy@berkeley.edu
Requires-Python: >=3.10,<4.0
Classifier: Programming Language :: Python :: 3
Classifier: Programming Language :: Python :: 3.10
Classifier: Programming Language :: Python :: 3.11
Requires-Dist: requests (>=2.32.3,<3.0.0)
